yf/__init__.py
yf-0.0.5.dist-info/licenses/LICENSE
yf-0.0.5.dist-info/METADATA
yf-0.0.5.dist-info/WHEEL
yf-0.0.5.dist-info/top_level.txt
yf-0.0.5.dist-info/RECORD
