Metadata-Version: 2.4
Name: yf
Version: 0.0.5
Summary: Diagnosing dictionaries
Home-page: https://github.com/t-c-w/yf
Author: Thor Whalen
License: apache-2.0
Platform: any
License-File: LICENSE
Dynamic: license-file
